rivalz_client/__init__.py
rivalz_client/client.py
tests/__init__.py
tests/test_client.py
rivalz_client-1.0.1.dist-info/LICENSE
rivalz_client-1.0.1.dist-info/METADATA
rivalz_client-1.0.1.dist-info/WHEEL
rivalz_client-1.0.1.dist-info/top_level.txt
rivalz_client-1.0.1.dist-info/RECORD
