Metadata-Version: 2.1
Name: rivalz-client
Version: 1.0.1
Summary: A Python client for interacting with Rivalz API
Home-page: https://github.com/Rivalz-ai/pyhon-client/
Author: Bui Dinh Ngoc
Author-email: buidinhngoc.aiti@gmail.com
Classifier: Programming Language :: Python :: 3
Classifier: License :: OSI Approved :: MIT License
Classifier: Operating System :: OS Independent
Requires-Python: >=3.6
License-File: LICENSE
Requires-Dist: requests >=2.28.2
Requires-Dist: python-dotenv >=1.0.0
